main.py
e4-0.0.0.dist-info/METADATA
e4-0.0.0.dist-info/WHEEL
e4-0.0.0.dist-info/top_level.txt
e4-0.0.0.dist-info/RECORD
