Metadata-Version: 2.1
Name: e4
Version: 0.0.0
Summary: e4 is in early development
Home-page: https://github.com/trevorbayless/e4
Author: Trevor Bayless
Author-email: UNKNOWN
License: UNKNOWN
Platform: UNKNOWN
